argunparse/__init__.py
argunparse/_version.py
argunparse/argument_unparser.py
argunparse/py.typed
argunparse-0.2.0.dist-info/licenses/LICENSE
argunparse-0.2.0.dist-info/licenses/NOTICE
argunparse-0.2.0.dist-info/METADATA
argunparse-0.2.0.dist-info/WHEEL
argunparse-0.2.0.dist-info/top_level.txt
argunparse-0.2.0.dist-info/RECORD
